ropey_py-0.3.1.dist-info/METADATA
ropey_py-0.3.1.dist-info/WHEEL
ropey_py/__init__.py
ropey_py/py.typed
ropey_py/ropey_py.cpython-310-i386-linux-gnu.so
ropey_py/ropey_py.pyi
ropey_py-0.3.1.dist-info/RECORD
