Metadata-Version: 2.4
Name: ropey-py
Version: 0.3.1
Classifier: Programming Language :: Rust
Classifier: Programming Language :: Python :: Implementation :: CPython
Classifier: Programming Language :: Python :: Implementation :: PyPy
Summary: Python bindings for the Ropey library
Keywords: rope,text,editor,buffer,python,rust
Author-email: Ivan Kosilov <idkosilov@gmail.com>
Requires-Python: >=3.8
